Metadata-Version: 2.1
Name: django-storages
Version: 1.14.4
Summary: Support for many storage backends in Django
Author-email: Josh Schneier <josh.schneier@gmail.com>
License: BSD-3-Clause
Project-URL: Homepage, https://github.com/jschneier/django-storages
Classifier: Development Status :: 5 - Production/Stable
Classifier: Environment :: Web Environment
Classifier: Framework :: Django
Classifier: Framework :: Django :: 3.2
Classifier: Framework :: Django :: 4.1
Classifier: Framework :: Django :: 4.2
Classifier: Framework :: Django :: 5.0
Classifier: Intended Audience :: Developers
Classifier: License :: OSI Approved :: BSD License
Classifier: Operating System :: OS Independent
Classifier: Programming Language :: Python
Classifier: Programming Language :: Python :: 3 :: Only
Classifier: Programming Language :: Python :: 3.7
Classifier: Programming Language :: Python :: 3.8
Classifier: Programming Language :: Python :: 3.9
Classifier: Programming Language :: Python :: 3.10
Classifier: Programming Language :: Python :: 3.11
Classifier: Programming Language :: Python :: 3.12
Requires-Python: >=3.7
Provides-Extra: azure
Provides-Extra: boto3
Provides-Extra: dropbox
Provides-Extra: google
Provides-Extra: libcloud
Provides-Extra: s3
Provides-Extra: sftp
License-File: LICENSE
